ML/MLRegressions.cp310-win_amd64.pyd
ML/__init__.py
MLRegressions-1.0.5.dist-info/LICENSE.txt
MLRegressions-1.0.5.dist-info/METADATA
MLRegressions-1.0.5.dist-info/WHEEL
MLRegressions-1.0.5.dist-info/top_level.txt
MLRegressions-1.0.5.dist-info/RECORD
