Metadata-Version: 2.1
Name: MLRegressions
Version: 1.0.5
Summary: 5 ML Model are available to train bassed on provided dataset, user can select one regresion out of 5 for train.
Author: DKVG
Author-email: gadellidk@gmail.com
Keywords: ML Regressions,MLRegressions Linear polynomial svr random-forest decision-tree regressors
Classifier: Programming Language :: Python :: 3
Classifier: License :: OSI Approved :: MIT License
Classifier: Operating System :: OS Independent
Requires-Python: >=3.10
License-File: LICENSE.txt
